README.md
setup.py
flask_servicefusion.egg-info/PKG-INFO
flask_servicefusion.egg-info/SOURCES.txt
flask_servicefusion.egg-info/dependency_links.txt
flask_servicefusion.egg-info/requires.txt
flask_servicefusion.egg-info/top_level.txt
servicefusion/JSONHandler.py
servicefusion/Servicefusion.py
servicefusion/ServicefusionToken.py
servicefusion/__init__.py
servicefusion/exceptions.py
servicefusion/REST/BaseService.py
servicefusion/REST/REST_V1.py
servicefusion/REST/__init__.py
servicefusion/REST/models.py
servicefusion/REST/V1/CustomerService.py
servicefusion/REST/V1/JobService.py
servicefusion/REST/V1/__init__.py
servicefusion/REST/V1/mixins.py
servicefusion/storages/BaseStorage.py
servicefusion/storages/InMemoryStorage.py
servicefusion/storages/JSONStorage.py
servicefusion/storages/__init__.py